pydo/__init__.py
pydo/config.py
pydo/exceptions.py
pydo/py.typed
pydo/services.py
pydo/types.py
pydo/version.py
pydo/views.py
pydo/entrypoints/__init__.py
pydo/entrypoints/cli.py
pydo/entrypoints/utils.py
pydo/model/__init__.py
pydo/model/date.py
pydo/model/task.py
pydo/model/views.py
py_do-0.1.1.dist-info/LICENSE
py_do-0.1.1.dist-info/METADATA
py_do-0.1.1.dist-info/WHEEL
py_do-0.1.1.dist-info/entry_points.txt
py_do-0.1.1.dist-info/top_level.txt
py_do-0.1.1.dist-info/RECORD
