Metadata-Version: 2.1
Name: py-do
Version: 0.1.1
Summary: Free software command line task manager built in Python.
Home-page: https://github.com/lyz-code/pydo
Author: Lyz
Author-email: lyz-code-security-advisories@riseup.net
License: GNU General Public License v3
Platform: UNKNOWN
Classifier: Development Status :: 2 - Pre-Alpha
Classifier: Intended Audience :: Developers
Classifier: License :: OSI Approved :: GNU General Public License v3 or later (GPLv3+)
Classifier: Operating System :: Unix
Classifier: Operating System :: POSIX
Classifier: Programming Language :: Python
Classifier: Programming Language :: Python :: 3
Classifier: Programming Language :: Python :: 3.7
Classifier: Programming Language :: Python :: 3.8
Classifier: Topic :: Utilities
Classifier: Natural Language :: English
Requires-Python: >=3.7
License-File: LICENSE
Requires-Dist: click
Requires-Dist: click-default-group
Requires-Dist: repository-orm
Requires-Dist: rich
Requires-Dist: python-dateutil
Requires-Dist: ulid-py
Requires-Dist: ruyaml
